vkessm_sdk.cpython-38-x86_64-linux-gnu.so
vkessm_sdk-1.3.0.dist-info/LICENSE.txt
vkessm_sdk-1.3.0.dist-info/METADATA
vkessm_sdk-1.3.0.dist-info/WHEEL
vkessm_sdk-1.3.0.dist-info/top_level.txt
vkessm_sdk-1.3.0.dist-info/RECORD
