Metadata-Version: 2.1
Name: vkessm-sdk
Version: 1.3.0
Summary: vkessm SDK 3. python package
Home-page: UNKNOWN
Author: vk
Author-email: vk@vkrobot.com
License: Apache 2.0
Platform: UNKNOWN
Requires-Dist: pyserial
